behave_django/__init__.py
behave_django/decorators.py
behave_django/environment.py
behave_django/pageobject.py
behave_django/runner.py
behave_django/testcase.py
behave_django/management/__init__.py
behave_django/management/commands/__init__.py
behave_django/management/commands/behave.py
behave_django-1.8.0.dist-info/licenses/AUTHORS.rst
behave_django-1.8.0.dist-info/licenses/LICENSE
behave_django-1.8.0.dist-info/METADATA
behave_django-1.8.0.dist-info/WHEEL
behave_django-1.8.0.dist-info/top_level.txt
behave_django-1.8.0.dist-info/RECORD
