Metadata-Version: 2.4
Name: behave-django
Version: 1.8.0
Summary: Behave BDD integration for Django
Author-email: Mitchel Cabuloy <mixxorz@gmail.com>, Peter Bittner <django@bittner.it>
Maintainer-email: Peter Bittner <django@bittner.it>, Javier Buzzi <buzzi.javier@gmail.com>
License-Expression: MIT
Project-URL: Source, https://github.com/behave/behave-django
Project-URL: Documentation, https://behave-django.readthedocs.io/
Keywords: bdd,behave,django,testing
Classifier: Development Status :: 5 - Production/Stable
Classifier: Environment :: Console
Classifier: Environment :: Plugins
Classifier: Environment :: Web Environment
Classifier: Framework :: Django
Classifier: Framework :: Django :: 4.2
Classifier: Framework :: Django :: 5.0
Classifier: Framework :: Django :: 5.1
Classifier: Framework :: Django :: 5.2
Classifier: Intended Audience :: Developers
Classifier: Operating System :: OS Independent
Classifier: Programming Language :: Python
Classifier: Programming Language :: Python :: 3
Classifier: Programming Language :: Python :: 3.9
Classifier: Programming Language :: Python :: 3.10
Classifier: Programming Language :: Python :: 3.11
Classifier: Programming Language :: Python :: 3.12
Classifier: Programming Language :: Python :: 3.13
Classifier: Programming Language :: Python :: 3.14
Classifier: Topic :: Internet :: WWW/HTTP
Classifier: Topic :: Internet :: WWW/HTTP :: Dynamic Content
Classifier: Topic :: Software Development :: Testing
Requires-Python: >=3.9
License-File: LICENSE
License-File: AUTHORS.rst
Requires-Dist: behave>=1.3.3
Requires-Dist: django>=4.2
Requires-Dist: beautifulsoup4
Dynamic: license-file
